dwave_sage_sampler.cp36-win_amd64.pyd
dwave_sage/__init__.py
dwave_sage/dimod_general_sa.py
dwave_sage-0.1.1.dist-info/DESCRIPTION.rst
dwave_sage-0.1.1.dist-info/METADATA
dwave_sage-0.1.1.dist-info/RECORD
dwave_sage-0.1.1.dist-info/WHEEL
dwave_sage-0.1.1.dist-info/metadata.json
dwave_sage-0.1.1.dist-info/top_level.txt
