Metadata-Version: 2.0
Name: dwave-sage
Version: 0.1.1
Summary: General Ising graph simulated annealing solver
Home-page: UNKNOWN
Author: William Bernoudy
Author-email: wbernoudy@dwavesys.com
License: Apache 2.0
Platform: UNKNOWN
Requires-Dist: numpy
Requires-Dist: dimod
